skrare/__init__.py
skrare/methods.py
skrare/multi_methods.py
skrare/rare.py
scikit_rare-0.9.2.dist-info/LICENSE
scikit_rare-0.9.2.dist-info/METADATA
scikit_rare-0.9.2.dist-info/WHEEL
scikit_rare-0.9.2.dist-info/top_level.txt
scikit_rare-0.9.2.dist-info/RECORD
