Metadata-Version: 2.1
Name: scikit-rare
Version: 0.9.2
Summary: A Scikit Learn compatible implementation of RARE Algorithm
Home-page: https://github.com/UrbsLab/scikit-RARE
Author: Harsh Bandhey
Author-email: harsh.bandhey@cshs.org
Classifier: Programming Language :: Python :: 3
Classifier: License :: OSI Approved :: MIT License
Classifier: Operating System :: OS Independent
Requires-Python: >=3.6
License-File: LICENSE
Requires-Dist: numpy
Requires-Dist: pandas
Requires-Dist: sklearn
Requires-Dist: lifelines
Requires-Dist: skrebate (==0.7)
Requires-Dist: matplotlib
